{"initial_variables":{"variable_group":"source","variables":[{"full_name":"source_address","name":"address","value":"4640 Admiralty Way, Marina Del Rey, CA 90292, USA"},{"full_name":"source_latitude","name":"latitude","value":33.9816425},{"full_name":"source_longitude","name":"longitude","value":-118.4409761}]},"duration":373.19872307777405,"agent_name":"Chris","events":[{"variables":[{"full_name":"u1_0","name":0,"value":"I"},{"full_name":"u1_1","name":1,"value":"'d"},{"full_name":"u1_2","name":2,"value":"like"},{"full_name":"u1_3","name":3,"value":"to"},{"full_name":"u1_4","name":4,"value":"go"},{"full_name":"u1_5","name":5,"value":"to"},{"full_name":"u1_6","name":6,"value":"the"},{"full_name":"u1_7","name":7,"value":"boxing"},{"full_name":"u1_8","name":8,"value":"match"},{"full_name":"u1_9","name":9,"value":","},{"full_name":"u1_10","name":10,"value":"it"},{"full_name":"u1_11","name":11,"value":"'s"},{"full_name":"u1_12","name":12,"value":"at"},{"full_name":"u1_13","name":13,"value":"a"},{"full_name":"u1_14","name":14,"value":"large"},{"full_name":"u1_15","name":15,"value":"venue"},{"full_name":"u1_16","name":16,"value":","},{"full_name":"u1_17","name":17,"value":"not"},{"full_name":"u1_18","name":18,"value":"Staples"},{"full_name":"u1_19","name":19,"value":"Center"},{"full_name":"u1_20","name":20,"value":"."}],"utterance":"I'd like to go to the boxing match, it's at a large venue, not Staples Center.","event_type":"user_utterance"},{"params":[{"param":"query","value":"boxing match","variable_name":"u1_7 + \" \" + u1_8"},{"param":"src latitude","value":33.9816425,"variable_name":"source_latitude"},{"param":"src longitude","value":-118.4409761,"variable_name":"source_longitude"}],"endpoint":"find_place","variables":[{"full_name":"v1_name","name":"name","value":"Mongoose Fight System"},{"full_name":"v1_address","name":"address","value":"17228 Saticoy St, Van Nuys, CA 91406, United States"},{"full_name":"v1_latitude","name":"latitude","value":"34.207145"},{"full_name":"v1_longitude","name":"longitude","value":"-118.5080736"},{"name":"types","value":[{"full_name":"v1_types_0","name":0,"value":"gym"},{"full_name":"v1_types_1","name":1,"value":"health"},{"full_name":"v1_types_2","name":2,"value":"point of interest"},{"full_name":"v1_types_3","name":3,"value":"establishment"}]},{"full_name":"v1_rating","name":"rating","value":"0"},{"full_name":"v1_address_simple","name":"address_simple","value":"17228 Saticoy Street, Van Nuys"},{"full_name":"v1_street_number","name":"street_number","value":"17228"},{"full_name":"v1_street_name","name":"street_name","value":"Saticoy Street"},{"full_name":"v1_neighborhood","name":"neighborhood","value":"Van Nuys"},{"full_name":"v1_locality","name":"locality","value":"Los Angeles"},{"full_name":"v1_distance","name":"distance","value":"21.9 mi"},{"full_name":"v1_duration","name":"duration","value":"33 mins"}],"event_type":"api_call"},{"params":[{"param":"query","value":"boxing match large venue","variable_name":"u1_7 + \" \" + u1_8 + \" \" + u1_14 + \" \" + u1_15"},{"param":"src latitude","value":33.9816425,"variable_name":"source_latitude"},{"param":"src longitude","value":-118.4409761,"variable_name":"source_longitude"}],"endpoint":"find_place","variables":[],"event_type":"api_call"},{"params":[{"param":"query","value":"large boxing venue","variable_name":"u1_14 + \" \" + u1_7 + \" \" + u1_15"},{"param":"src latitude","value":33.9816425,"variable_name":"source_latitude"},{"param":"src longitude","value":-118.4409761,"variable_name":"source_longitude"}],"endpoint":"places_nearby","variables":[],"event_type":"api_call"},{"params":[{"param":"query","value":"boxing match venue","variable_name":"u1_7 + \" \" + u1_8 + \" \" + u1_15"},{"param":"src latitude","value":33.9816425,"variable_name":"source_latitude"},{"param":"src longitude","value":-118.4409761,"variable_name":"source_longitude"}],"endpoint":"find_place","variables":[{"full_name":"v4_name","name":"name","value":"Dignity Health Sports Park"},{"full_name":"v4_address","name":"address","value":"18400 S Avalon Blvd, Carson, CA 90746, United States"},{"full_name":"v4_latitude","name":"latitude","value":"33.8643777"},{"full_name":"v4_longitude","name":"longitude","value":"-118.2611426"},{"name":"types","value":[{"full_name":"v4_types_0","name":0,"value":"stadium"},{"full_name":"v4_types_1","name":1,"value":"gym"},{"full_name":"v4_types_2","name":2,"value":"health"},{"full_name":"v4_types_3","name":3,"value":"point of interest"},{"full_name":"v4_types_4","name":4,"value":"establishment"}]},{"full_name":"v4_rating","name":"rating","value":"4.5"},{"full_name":"v4_address_simple","name":"address_simple","value":"18400 South Avalon Boulevard, Carson"},{"full_name":"v4_street_number","name":"street_number","value":"18400"},{"full_name":"v4_street_name","name":"street_name","value":"South Avalon Boulevard"},{"full_name":"v4_locality","name":"locality","value":"Carson"},{"full_name":"v4_distance","name":"distance","value":"17.5 mi"},{"full_name":"v4_duration","name":"duration","value":"27 mins"}],"event_type":"api_call"},{"params":["v4_types_0","v4_name","v4_street_name","v4_locality"],"template":"I found a {} called {} on {} in {}.","utterance":"I found a stadium called Dignity Health Sports Park on South Avalon Boulevard in Carson.","event_type":"agent_utterance"},{"variables":[{"full_name":"u2_0","name":0,"value":"Oh"},{"full_name":"u2_1","name":1,"value":","},{"full_name":"u2_2","name":2,"value":"I"},{"full_name":"u2_3","name":3,"value":"know"},{"full_name":"u2_4","name":4,"value":"that"},{"full_name":"u2_5","name":5,"value":"one"},{"full_name":"u2_6","name":6,"value":"."},{"full_name":"u2_7","name":7,"value":"That"},{"full_name":"u2_8","name":8,"value":"'s"},{"full_name":"u2_9","name":9,"value":"too"},{"full_name":"u2_10","name":10,"value":"far"},{"full_name":"u2_11","name":11,"value":"the"},{"full_name":"u2_12","name":12,"value":"one"},{"full_name":"u2_13","name":13,"value":"I"},{"full_name":"u2_14","name":14,"value":"'m"},{"full_name":"u2_15","name":15,"value":"thinking"},{"full_name":"u2_16","name":16,"value":"of"},{"full_name":"u2_17","name":17,"value":"is"},{"full_name":"u2_18","name":18,"value":"where"},{"full_name":"u2_19","name":19,"value":"the"},{"full_name":"u2_20","name":20,"value":"Lakers"},{"full_name":"u2_21","name":21,"value":"used"},{"full_name":"u2_22","name":22,"value":"to"},{"full_name":"u2_23","name":23,"value":"play"},{"full_name":"u2_24","name":24,"value":"."}],"utterance":"Oh, I know that one. That's too far the one I'm thinking of is where the Lakers used to play.","event_type":"user_utterance"},{"variables":[{"full_name":"u3_0","name":0,"value":"I"},{"full_name":"u3_1","name":1,"value":"believe"},{"full_name":"u3_2","name":2,"value":"it"},{"full_name":"u3_3","name":3,"value":"'s"},{"full_name":"u3_4","name":4,"value":"in"},{"full_name":"u3_5","name":5,"value":"Inglewood"},{"full_name":"u3_6","name":6,"value":"."}],"utterance":"I believe it's in Inglewood.","event_type":"user_utterance"},{"params":[{"param":"query","value":"where the Lakers used to play","variable_name":"u2_18 + \" \" + u2_19 + \" \" + u2_20 + \" \" + u2_21 + \" \" + u2_22 + \" \" + u2_23"},{"param":"src latitude","value":33.9816425,"variable_name":"source_latitude"},{"param":"src longitude","value":-118.4409761,"variable_name":"source_longitude"}],"endpoint":"find_place","variables":[],"event_type":"api_call"},{"params":[{"param":"query","value":"Inglewood","variable_name":"u3_5"},{"param":"src latitude","value":33.9816425,"variable_name":"source_latitude"},{"param":"src longitude","value":-118.4409761,"variable_name":"source_longitude"}],"endpoint":"find_place","variables":[{"full_name":"v6_name","name":"name","value":"Inglewood"},{"full_name":"v6_address","name":"address","value":"Inglewood, CA, USA"},{"full_name":"v6_latitude","name":"latitude","value":"33.9616801"},{"full_name":"v6_longitude","name":"longitude","value":"-118.3531311"},{"name":"types","value":[{"full_name":"v6_types_0","name":0,"value":"locality"},{"full_name":"v6_types_1","name":1,"value":"political"}]},{"full_name":"v6_address_simple","name":"address_simple","value":"Inglewood"},{"full_name":"v6_locality","name":"locality","value":"Inglewood"},{"full_name":"v6_distance","name":"distance","value":"6.5 mi"},{"full_name":"v6_duration","name":"duration","value":"14 mins"}],"event_type":"api_call"},{"params":[{"param":"query","value":"Lakers play","variable_name":"u2_20 + \" \" + u2_23"},{"param":"src latitude","value":"33.9616801","variable_name":"v6_latitude"},{"param":"src longitude","value":"-118.3531311","variable_name":"v6_longitude"}],"endpoint":"find_place","variables":[{"full_name":"v7_name","name":"name","value":"Los Angeles Lakers"},{"full_name":"v7_address","name":"address","value":"2275 E Mariposa Ave, El Segundo, CA 90245, United States"},{"full_name":"v7_latitude","name":"latitude","value":"33.9242555"},{"full_name":"v7_longitude","name":"longitude","value":"-118.3840595"},{"name":"types","value":[{"full_name":"v7_types_0","name":0,"value":"point of interest"},{"full_name":"v7_types_1","name":1,"value":"establishment"}]},{"full_name":"v7_rating","name":"rating","value":"4.4"},{"full_name":"v7_is_open","name":"is_open","value":"True"},{"full_name":"v7_address_simple","name":"address_simple","value":"2275 East Mariposa Avenue, El Segundo"},{"full_name":"v7_street_number","name":"street_number","value":"2275"},{"full_name":"v7_street_name","name":"street_name","value":"East Mariposa Avenue"},{"full_name":"v7_locality","name":"locality","value":"El Segundo"},{"full_name":"v7_distance","name":"distance","value":"5.2 mi"},{"full_name":"v7_duration","name":"duration","value":"13 mins"}],"event_type":"api_call"},{"variables":[{"full_name":"u4_0","name":0,"value":"The"},{"full_name":"u4_1","name":1,"value":"venue"},{"full_name":"u4_2","name":2,"value":"is"},{"full_name":"u4_3","name":3,"value":"huge"},{"full_name":"u4_4","name":4,"value":","},{"full_name":"u4_5","name":5,"value":"it"},{"full_name":"u4_6","name":6,"value":"holds"},{"full_name":"u4_7","name":7,"value":"large"},{"full_name":"u4_8","name":8,"value":"concerts"},{"full_name":"u4_9","name":9,"value":"and"},{"full_name":"u4_10","name":10,"value":"sporting"},{"full_name":"u4_11","name":11,"value":"events"},{"full_name":"u4_12","name":12,"value":"."}],"utterance":"The venue is huge, it holds large concerts and sporting events.","event_type":"user_utterance"},{"params":[{"param":"query","value":"large concerts and sporting events","variable_name":"u4_7 + \" \" + u4_8 + \" \" + u4_9 + \" \" + u4_10 + \" \" + u4_11"},{"param":"src latitude","value":"33.9616801","variable_name":"v6_latitude"},{"param":"src longitude","value":"-118.3531311","variable_name":"v6_longitude"}],"endpoint":"find_place","variables":[{"full_name":"v8_name","name":"name","value":"The Forum"},{"full_name":"v8_address","name":"address","value":"3900 W Manchester Blvd, Inglewood, CA 90305, United States"},{"full_name":"v8_latitude","name":"latitude","value":"33.9582109"},{"full_name":"v8_longitude","name":"longitude","value":"-118.3419015"},{"name":"types","value":[{"full_name":"v8_types_0","name":0,"value":"point of interest"},{"full_name":"v8_types_1","name":1,"value":"establishment"}]},{"full_name":"v8_rating","name":"rating","value":"4.5"},{"full_name":"v8_is_open","name":"is_open","value":"True"},{"full_name":"v8_address_simple","name":"address_simple","value":"3900 West Manchester Boulevard, Inglewood"},{"full_name":"v8_street_number","name":"street_number","value":"3900"},{"full_name":"v8_street_name","name":"street_name","value":"West Manchester Boulevard"},{"full_name":"v8_neighborhood","name":"neighborhood","value":"South Los Angeles"},{"full_name":"v8_locality","name":"locality","value":"Inglewood"},{"full_name":"v8_distance","name":"distance","value":"1.0 mi"},{"full_name":"v8_duration","name":"duration","value":"5 mins"}],"event_type":"api_call"},{"params":["v8_name"],"template":"Do you mean {}?","utterance":"Do you mean The Forum?","event_type":"agent_utterance"},{"variables":[{"full_name":"u5_0","name":0,"value":"Yup"},{"full_name":"u5_1","name":1,"value":","},{"full_name":"u5_2","name":2,"value":"that"},{"full_name":"u5_3","name":3,"value":"'s"},{"full_name":"u5_4","name":4,"value":"it"},{"full_name":"u5_5","name":5,"value":"."}],"utterance":"Yup, that's it.","event_type":"user_utterance"},{"params":[],"template":"Shall we go?","utterance":"Shall we go?","event_type":"agent_utterance"},{"variables":[{"full_name":"u6_0","name":0,"value":"Yes"}],"utterance":"Yes","event_type":"user_utterance"},{"params":["v8_name"],"template":"Great, we are going to {}.","utterance":"Great, we are going to The Forum.","event_type":"agent_utterance"},{"destination":{"latitude":"33.9582109","longitude":"-118.3419015"},"start_driving":true,"event_type":"end_dialog"}],"api_key":"AIzaSyCLLEjJz56gh9tuKT_7KOTMZGdl7vdbkp4","correct_destination":true}
