{"initial_variables":{"variable_group":"source","variables":[{"full_name":"source_address","name":"address","value":"6535 Ravenna Ave NE, Seattle, WA 98115, United States"},{"full_name":"source_latitude","name":"latitude","value":47.676},{"full_name":"source_longitude","name":"longitude","value":-122.306}]},"duration":151.64069819450378,"agent_name":"yiqi","events":[{"variables":[{"full_name":"u1_0","name":0,"value":"bagel"},{"full_name":"u1_1","name":1,"value":"place"},{"full_name":"u1_2","name":2,"value":"please"}],"utterance":"bagel place please","event_type":"user_utterance"},{"variables":[{"full_name":"u2_0","name":0,"value":"the"},{"full_name":"u2_1","name":1,"value":"one"},{"full_name":"u2_2","name":2,"value":"on"},{"full_name":"u2_3","name":3,"value":"12th"}],"utterance":"the one on 12th","event_type":"user_utterance"},{"params":[{"param":"query","value":"12th","variable_name":"u2_3"},{"param":"src latitude","value":47.676,"variable_name":"source_latitude"},{"param":"src longitude","value":-122.306,"variable_name":"source_longitude"}],"endpoint":"find_place","variables":[{"full_name":"v1_name","name":"name","value":"12th Ave NE & NE 65th St"},{"full_name":"v1_address","name":"address","value":"Seattle, WA 98115, United States"},{"full_name":"v1_latitude","name":"latitude","value":"47.6760521"},{"full_name":"v1_longitude","name":"longitude","value":"-122.315567"},{"name":"types","value":[{"full_name":"v1_types_0","name":0,"value":"transit station"},{"full_name":"v1_types_1","name":1,"value":"point of interest"},{"full_name":"v1_types_2","name":2,"value":"establishment"}]},{"full_name":"v1_rating","name":"rating","value":"3"},{"full_name":"v1_address_simple","name":"address_simple","value":"United States"},{"full_name":"v1_neighborhood","name":"neighborhood","value":"Northeast Seattle"},{"full_name":"v1_locality","name":"locality","value":"Seattle"},{"full_name":"v1_distance","name":"distance","value":"0.5 mi"},{"full_name":"v1_duration","name":"duration","value":"2 mins"}],"event_type":"api_call"},{"params":[{"param":"query","value":"bagel place on 12th","variable_name":"u1_0 + \" \" + u1_1 + \" \" + u2_2 + \" \" + u2_3"},{"param":"src latitude","value":47.676,"variable_name":"source_latitude"},{"param":"src longitude","value":-122.306,"variable_name":"source_longitude"}],"endpoint":"find_place","variables":[{"full_name":"v2_name","name":"name","value":"Eltana"},{"full_name":"v2_address","name":"address","value":"1538 12th Ave, Seattle, WA 98122, United States"},{"full_name":"v2_latitude","name":"latitude","value":"47.6150271"},{"full_name":"v2_longitude","name":"longitude","value":"-122.3165276"},{"full_name":"v2_price_level","name":"price_level","value":"1"},{"name":"types","value":[{"full_name":"v2_types_0","name":0,"value":"bakery"},{"full_name":"v2_types_1","name":1,"value":"cafe"},{"full_name":"v2_types_2","name":2,"value":"restaurant"},{"full_name":"v2_types_3","name":3,"value":"food"},{"full_name":"v2_types_4","name":4,"value":"point of interest"},{"full_name":"v2_types_5","name":5,"value":"store"},{"full_name":"v2_types_6","name":6,"value":"establishment"}]},{"full_name":"v2_rating","name":"rating","value":"4.3"},{"full_name":"v2_is_open","name":"is_open","value":"True"},{"full_name":"v2_address_simple","name":"address_simple","value":"1538 12th Avenue, Seattle"},{"full_name":"v2_street_number","name":"street_number","value":"1538"},{"full_name":"v2_street_name","name":"street_name","value":"12th Avenue"},{"full_name":"v2_neighborhood","name":"neighborhood","value":"Capitol Hill"},{"full_name":"v2_locality","name":"locality","value":"Seattle"},{"full_name":"v2_distance","name":"distance","value":"5.3 mi"},{"full_name":"v2_duration","name":"duration","value":"16 mins"}],"event_type":"api_call"},{"params":["v2_name","v2_street_name"],"template":"I found {} on {}, is that ok?","utterance":"I found Eltana on 12th Avenue, is that ok?","event_type":"agent_utterance"},{"params":["v2_rating"],"template":"It has a rating of {}.","utterance":"It has a rating of 4.3.","event_type":"agent_utterance"},{"variables":[{"full_name":"u3_0","name":0,"value":"is"},{"full_name":"u3_1","name":1,"value":"that"},{"full_name":"u3_2","name":2,"value":"the"},{"full_name":"u3_3","name":3,"value":"12th"},{"full_name":"u3_4","name":4,"value":"on"},{"full_name":"u3_5","name":5,"value":"Capitol"},{"full_name":"u3_6","name":6,"value":"Hill"},{"full_name":"u3_7","name":7,"value":"?"}],"utterance":"is that the 12th on Capitol Hill?","event_type":"user_utterance"},{"params":[],"template":"Yes.","utterance":"Yes.","event_type":"agent_utterance"},{"params":["v2_distance","v2_duration"],"template":"It is {} and {} away.","utterance":"It is 5.3 mi and 16 mins away.","event_type":"agent_utterance"},{"params":[],"template":"Shall we go?","utterance":"Shall we go?","event_type":"agent_utterance"},{"variables":[{"full_name":"u4_0","name":0,"value":"lets"},{"full_name":"u4_1","name":1,"value":"roll"}],"utterance":"lets roll","event_type":"user_utterance"},{"destination":{"latitude":"47.6150271","longitude":"-122.3165276"},"start_driving":true,"event_type":"end_dialog"}],"api_key":"AIzaSyCLLEjJz56gh9tuKT_7KOTMZGdl7vdbkp4","correct_destination":true}
