{"initial_variables":{"variable_group":"source","variables":[{"full_name":"source_address","name":"address","value":"3507 Vía Dolce, Marina Del Rey, CA 90292, United States"},{"full_name":"source_latitude","name":"latitude","value":33.979},{"full_name":"source_longitude","name":"longitude","value":-118.46}]},"duration":148.47444343566895,"agent_name":"Chris","events":[{"variables":[{"full_name":"u1_0","name":0,"value":"I"},{"full_name":"u1_1","name":1,"value":"'d"},{"full_name":"u1_2","name":2,"value":"like"},{"full_name":"u1_3","name":3,"value":"to"},{"full_name":"u1_4","name":4,"value":"go"},{"full_name":"u1_5","name":5,"value":"clubbing"},{"full_name":"u1_6","name":6,"value":"downtown"}],"utterance":"I'd like to go clubbing downtown","event_type":"user_utterance"},{"params":[{"param":"query","value":"clubbing downtown","variable_name":"u1_5 + \" \" + u1_6"},{"param":"src latitude","value":33.979,"variable_name":"source_latitude"},{"param":"src longitude","value":-118.460,"variable_name":"source_longitude"}],"endpoint":"places_nearby","variables":[{"name":"0","value":[{"full_name":"v1_0_name","name":"name","value":"West End"},{"full_name":"v1_0_rating","name":"rating","value":"3.7"},{"full_name":"v1_0_is_open","name":"is_open","value":"False"},{"name":"types","value":[{"full_name":"v1_0_types_0","name":0,"value":"night club"},{"full_name":"v1_0_types_1","name":1,"value":"bar"},{"full_name":"v1_0_types_2","name":2,"value":"point of interest"},{"full_name":"v1_0_types_3","name":3,"value":"establishment"}]},{"full_name":"v1_0_latitude","name":"latitude","value":"34.0185186"},{"full_name":"v1_0_longitude","name":"longitude","value":"-118.4956006"},{"full_name":"v1_0_address_simple","name":"address_simple","value":"1301 5th Street, Santa Monica"},{"full_name":"v1_0_street_number","name":"street_number","value":"1301"},{"full_name":"v1_0_street_name","name":"street_name","value":"5th Street"},{"full_name":"v1_0_neighborhood","name":"neighborhood","value":"Downtown"},{"full_name":"v1_0_locality","name":"locality","value":"Santa Monica"},{"full_name":"v1_0_distance","name":"distance","value":"3.9 mi"},{"full_name":"v1_0_duration","name":"duration","value":"19 mins"}]},{"name":"1","value":[{"full_name":"v1_1_name","name":"name","value":"Senator Jones"},{"full_name":"v1_1_rating","name":"rating","value":"3.2"},{"name":"types","value":[{"full_name":"v1_1_types_0","name":0,"value":"night club"},{"full_name":"v1_1_types_1","name":1,"value":"point of interest"},{"full_name":"v1_1_types_2","name":2,"value":"establishment"}]},{"full_name":"v1_1_latitude","name":"latitude","value":"34.0316751"},{"full_name":"v1_1_longitude","name":"longitude","value":"-118.4823997"},{"full_name":"v1_1_address_simple","name":"address_simple","value":"2020 Wilshire Boulevard, Santa Monica"},{"full_name":"v1_1_street_number","name":"street_number","value":"2020"},{"full_name":"v1_1_street_name","name":"street_name","value":"Wilshire Boulevard"},{"full_name":"v1_1_neighborhood","name":"neighborhood","value":"Mid-City"},{"full_name":"v1_1_locality","name":"locality","value":"Santa Monica"},{"full_name":"v1_1_distance","name":"distance","value":"5.5 mi"},{"full_name":"v1_1_duration","name":"duration","value":"22 mins"}]},{"name":"2","value":[{"full_name":"v1_2_name","name":"name","value":"Carbon"},{"full_name":"v1_2_rating","name":"rating","value":"3.7"},{"full_name":"v1_2_is_open","name":"is_open","value":"False"},{"full_name":"v1_2_price_level","name":"price_level","value":"2"},{"name":"types","value":[{"full_name":"v1_2_types_0","name":0,"value":"night club"},{"full_name":"v1_2_types_1","name":1,"value":"bar"},{"full_name":"v1_2_types_2","name":2,"value":"point of interest"},{"full_name":"v1_2_types_3","name":3,"value":"establishment"}]},{"full_name":"v1_2_latitude","name":"latitude","value":"34.0257228"},{"full_name":"v1_2_longitude","name":"longitude","value":"-118.3941224"},{"full_name":"v1_2_address_simple","name":"address_simple","value":"9300 Venice Boulevard, Culver City"},{"full_name":"v1_2_street_number","name":"street_number","value":"9300"},{"full_name":"v1_2_street_name","name":"street_name","value":"Venice Boulevard"},{"full_name":"v1_2_neighborhood","name":"neighborhood","value":"Downtown"},{"full_name":"v1_2_locality","name":"locality","value":"Culver City"},{"full_name":"v1_2_distance","name":"distance","value":"5.4 mi"},{"full_name":"v1_2_duration","name":"duration","value":"21 mins"}]}],"event_type":"api_call"},{"params":[{"param":"query","value":"downtown","variable_name":"u1_6"},{"param":"src latitude","value":33.979,"variable_name":"source_latitude"},{"param":"src longitude","value":-118.460,"variable_name":"source_longitude"}],"endpoint":"find_place","variables":[{"full_name":"v2_name","name":"name","value":"Downtown Los Angeles"},{"full_name":"v2_address","name":"address","value":"Downtown Los Angeles, Los Angeles, CA, USA"},{"full_name":"v2_latitude","name":"latitude","value":"34.040713"},{"full_name":"v2_longitude","name":"longitude","value":"-118.2467693"},{"name":"types","value":[{"full_name":"v2_types_0","name":0,"value":"neighborhood"},{"full_name":"v2_types_1","name":1,"value":"political"}]},{"full_name":"v2_address_simple","name":"address_simple","value":"Los Angeles"},{"full_name":"v2_neighborhood","name":"neighborhood","value":"Downtown Los Angeles"},{"full_name":"v2_locality","name":"locality","value":"Los Angeles"},{"full_name":"v2_distance","name":"distance","value":"19.6 mi"},{"full_name":"v2_duration","name":"duration","value":"35 mins"}],"event_type":"api_call"},{"params":[{"param":"query","value":"clubbing","variable_name":"u1_5"},{"param":"src latitude","value":"34.040713","variable_name":"v2_latitude"},{"param":"src longitude","value":"-118.2467693","variable_name":"v2_longitude"}],"endpoint":"places_nearby","variables":[{"name":"0","value":[{"full_name":"v3_0_name","name":"name","value":"The Reserve"},{"full_name":"v3_0_rating","name":"rating","value":"3.7"},{"full_name":"v3_0_is_open","name":"is_open","value":"False"},{"full_name":"v3_0_price_level","name":"price_level","value":"2"},{"name":"types","value":[{"full_name":"v3_0_types_0","name":0,"value":"night club"},{"full_name":"v3_0_types_1","name":1,"value":"bar"},{"full_name":"v3_0_types_2","name":2,"value":"point of interest"},{"full_name":"v3_0_types_3","name":3,"value":"establishment"}]},{"full_name":"v3_0_latitude","name":"latitude","value":"34.0447027"},{"full_name":"v3_0_longitude","name":"longitude","value":"-118.2519124"},{"full_name":"v3_0_address_simple","name":"address_simple","value":"650 South Spring Street, Los Angeles"},{"full_name":"v3_0_street_number","name":"street_number","value":"650"},{"full_name":"v3_0_street_name","name":"street_name","value":"South Spring Street"},{"full_name":"v3_0_neighborhood","name":"neighborhood","value":"Downtown Los Angeles"},{"full_name":"v3_0_locality","name":"locality","value":"Los Angeles"},{"full_name":"v3_0_distance","name":"distance","value":"0.9 mi"},{"full_name":"v3_0_duration","name":"duration","value":"7 mins"}]},{"name":"1","value":[{"full_name":"v3_1_name","name":"name","value":"Exchange LA"},{"full_name":"v3_1_rating","name":"rating","value":"3.9"},{"full_name":"v3_1_is_open","name":"is_open","value":"False"},{"full_name":"v3_1_price_level","name":"price_level","value":"3"},{"name":"types","value":[{"full_name":"v3_1_types_0","name":0,"value":"night club"},{"full_name":"v3_1_types_1","name":1,"value":"point of interest"},{"full_name":"v3_1_types_2","name":2,"value":"establishment"}]},{"full_name":"v3_1_latitude","name":"latitude","value":"34.0453777"},{"full_name":"v3_1_longitude","name":"longitude","value":"-118.2513164"},{"full_name":"v3_1_address_simple","name":"address_simple","value":"618 South Spring Street, Los Angeles"},{"full_name":"v3_1_street_number","name":"street_number","value":"618"},{"full_name":"v3_1_street_name","name":"street_name","value":"South Spring Street"},{"full_name":"v3_1_neighborhood","name":"neighborhood","value":"Downtown Los Angeles"},{"full_name":"v3_1_locality","name":"locality","value":"Los Angeles"},{"full_name":"v3_1_distance","name":"distance","value":"0.9 mi"},{"full_name":"v3_1_duration","name":"duration","value":"6 mins"}]},{"name":"2","value":[{"full_name":"v3_2_name","name":"name","value":"Los Angeles Club Crawl"},{"full_name":"v3_2_rating","name":"rating","value":"4"},{"full_name":"v3_2_is_open","name":"is_open","value":"False"},{"name":"types","value":[{"full_name":"v3_2_types_0","name":0,"value":"night club"},{"full_name":"v3_2_types_1","name":1,"value":"travel agency"},{"full_name":"v3_2_types_2","name":2,"value":"bar"},{"full_name":"v3_2_types_3","name":3,"value":"point of interest"},{"full_name":"v3_2_types_4","name":4,"value":"establishment"}]},{"full_name":"v3_2_latitude","name":"latitude","value":"34.0451292"},{"full_name":"v3_2_longitude","name":"longitude","value":"-118.2528925"},{"full_name":"v3_2_address_simple","name":"address_simple","value":"221 West 7th Street, Los Angeles"},{"full_name":"v3_2_street_number","name":"street_number","value":"221"},{"full_name":"v3_2_street_name","name":"street_name","value":"West 7th Street"},{"full_name":"v3_2_neighborhood","name":"neighborhood","value":"Downtown Los Angeles"},{"full_name":"v3_2_locality","name":"locality","value":"Los Angeles"},{"full_name":"v3_2_distance","name":"distance","value":"0.5 mi"},{"full_name":"v3_2_duration","name":"duration","value":"4 mins"}]}],"event_type":"api_call"},{"params":["v3_0_name","v3_1_name","v3_2_name"],"template":"I found three places: {}, {}, and {}.","utterance":"I found three places: The Reserve, Exchange LA, and Los Angeles Club Crawl.","event_type":"agent_utterance"},{"params":["v3_0_rating","v3_1_rating","v3_2_rating"],"template":"Their ratings are {}, {} and {} respectively.","utterance":"Their ratings are 3.7, 3.9 and 4 respectively.","event_type":"agent_utterance"},{"variables":[{"full_name":"u2_0","name":0,"value":"Hm"},{"full_name":"u2_1","name":1,"value":"ok"},{"full_name":"u2_2","name":2,"value":","},{"full_name":"u2_3","name":3,"value":"let"},{"full_name":"u2_4","name":4,"value":"'s"},{"full_name":"u2_5","name":5,"value":"go"},{"full_name":"u2_6","name":6,"value":"to"},{"full_name":"u2_7","name":7,"value":"Exchange"}],"utterance":"Hm ok, let's go to Exchange","event_type":"user_utterance"},{"destination":{"latitude":"34.0453777","longitude":"-118.2513164"},"start_driving":true,"event_type":"end_dialog"}],"api_key":"AIzaSyCLLEjJz56gh9tuKT_7KOTMZGdl7vdbkp4","correct_destination":true}
